filebox/__init__.py
filebox/excel.py
filebox/filebox.py
filebox/pathx.py
filebox-0.0.12.dist-info/METADATA
filebox-0.0.12.dist-info/WHEEL
filebox-0.0.12.dist-info/top_level.txt
filebox-0.0.12.dist-info/RECORD
