Metadata-Version: 2.1
Name: filebox
Version: 0.0.12
Summary: make it easy to manage file
Home-page: https://gitee.com/ZeroSeeker/filebox
Author: ZeroSeeker
Author-email: zeroseeker@foxmail.com
License: UNKNOWN
Platform: UNKNOWN
Classifier: Programming Language :: Python :: 3
Classifier: License :: OSI Approved :: MIT License
Classifier: Operating System :: OS Independent
Requires-Dist: requests (==2.27.1)
Requires-Dist: showlog (==0.0.6)
Requires-Dist: urllib3 (==1.26.9)
Requires-Dist: xlrd (==2.0.1)
Requires-Dist: openpyxl (==3.0.9)
Requires-Dist: dictbox (==0.0.2)
